classicist/__init__.py
classicist/version.txt
classicist/decorators/__init__.py
classicist/decorators/aliased/__init__.py
classicist/decorators/annotation/__init__.py
classicist/decorators/classproperty/__init__.py
classicist/decorators/deprecated/__init__.py
classicist/decorators/hybridmethod/__init__.py
classicist/decorators/nocache/__init__.py
classicist/exceptions/__init__.py
classicist/exceptions/decorators/__init__.py
classicist/exceptions/decorators/aliased/__init__.py
classicist/exceptions/decorators/annotation/__init__.py
classicist/exceptions/metaclasses/__init__.py
classicist/exceptions/metaclasses/shadowproof/__init__.py
classicist/inspector/__init__.py
classicist/logging/__init__.py
classicist/metaclasses/__init__.py
classicist/metaclasses/aliased/__init__.py
classicist/metaclasses/shadowproof/__init__.py
classicist-1.0.3.dist-info/licenses/LICENSE.md
classicist-1.0.3.dist-info/METADATA
classicist-1.0.3.dist-info/WHEEL
classicist-1.0.3.dist-info/top_level.txt
classicist-1.0.3.dist-info/zip-safe
classicist-1.0.3.dist-info/RECORD
