Metadata-Version: 2.4
Name: classicist
Version: 1.0.3
Summary: Classy class decorators for Python.
Author: Daniel Sissman
License-Expression: MIT
Project-URL: documentation, https://github.com/bluebinary/classicist/blob/main/README.md
Project-URL: changelog, https://github.com/bluebinary/classicist/blob/main/CHANGELOG.md
Project-URL: repository, https://github.com/bluebinary/classicist
Project-URL: issues, https://github.com/bluebinary/classicist/issues
Project-URL: homepage, https://github.com/bluebinary/classicist
Keywords: decorator,hybrid method,class method,instance method,class property,class properties,annotations,deprecations,aliases,shadow proofing
Classifier: Programming Language :: Python :: 3
Classifier: Programming Language :: Python :: 3.9
Classifier: Programming Language :: Python :: 3.10
Classifier: Programming Language :: Python :: 3.11
Classifier: Programming Language :: Python :: 3.12
Classifier: Programming Language :: Python :: 3.13
Classifier: Programming Language :: Python :: 3.14
Requires-Python: >=3.9
License-File: LICENSE.md
Provides-Extra: development
Requires-Dist: black==26.1.*; extra == "development"
Requires-Dist: pytest==8.3.*; extra == "development"
Requires-Dist: pytest-codeblocks==0.17.0; extra == "development"
Requires-Dist: pyflakes; extra == "development"
Provides-Extra: distribution
Requires-Dist: build; extra == "distribution"
Requires-Dist: twine; extra == "distribution"
Requires-Dist: wheel; extra == "distribution"
Dynamic: license-file
